async_bitfinex/__init__.py
async_bitfinex/rest/__init__.py
async_bitfinex/rest/restv1.py
async_bitfinex/rest/restv2.py
async_bitfinex/utils/__init__.py
async_bitfinex/websockets/__init__.py
async_bitfinex/websockets/abbreviations.py
async_bitfinex/websockets/client.py
async_bitfinex/websockets/futures_handler.py
examples/__init__.py
examples/basic.py
examples/message_handling.py
examples/more_examples.py
examples/new_websocket.py
tests/__init__.py
tests/test_rest_v1.py
tests/test_rest_v2.py
tests/test_utils.py
async_bitfinex-0.4.2.dist-info/LICENSE.md
async_bitfinex-0.4.2.dist-info/METADATA
async_bitfinex-0.4.2.dist-info/WHEEL
async_bitfinex-0.4.2.dist-info/top_level.txt
async_bitfinex-0.4.2.dist-info/zip-safe
async_bitfinex-0.4.2.dist-info/RECORD
